testreverseautoslitcode/LRIS_Mask_Coords_to_WCS.py
testreverseautoslitcode/__init__.py
testreverseautoslitcode/astrometrycorrection.py
testreverseautoslitcode/callcode.py
testreverseautoslitcode/create_err_plot.py
testreverseautoslitcode/find_shifts.py
testreverseautoslitcode/precessionroutine.py
testreverseautoslitcode/refractioncorrection.py
testreverseautoslitcode/write_ds9_file.py
testreverseautoslitcode-0.1.35.dist-info/WHEEL
testreverseautoslitcode-0.1.35.dist-info/METADATA
testreverseautoslitcode-0.1.35.dist-info/RECORD
