Metadata-Version: 2.1
Name: testreverseautoslitcode
Version: 0.1.35
Summary: Test Compiling of Code
Author: Jessica Sullivan
Author-email: jsulli27@nd.edu
Requires-Python: >=3.7,<4.0
Classifier: Programming Language :: Python :: 3
Classifier: Programming Language :: Python :: 3.7
Classifier: Programming Language :: Python :: 3.8
Classifier: Programming Language :: Python :: 3.9
Requires-Dist: astropy (==4.3.post1)
Requires-Dist: astroquery (==0.4.3)
Requires-Dist: matplotlib (==3.4.2)
Requires-Dist: numpy (==1.21.1)
Requires-Dist: panstamps (==0.6.1)
Requires-Dist: pytest-shutil (==1.7.0)
Requires-Dist: pyyaml (==5.3.1)
Requires-Dist: regions (==0.5)
Requires-Dist: shapely
